behavysis_classifier/__init__.py
behavysis_classifier/behav_classifier.py
behavysis_classifier/clf_models/__init__.py
behavysis_classifier/clf_models/base_torch_model.py
behavysis_classifier/clf_models/clf_templates.py
behavysis_classifier/pydantic_models/__init__.py
behavysis_classifier/pydantic_models/behav_classifier_configs.py
behavysis_classifier/scripts/__init__.py
behavysis_classifier/scripts/classifier_gui.py
behavysis_classifier/scripts/make_classifier.py
behavysis_classifier/templates/train_behav_classifier.py
behavysis_classifier-0.1.23.dist-info/LICENSE
behavysis_classifier-0.1.23.dist-info/METADATA
behavysis_classifier-0.1.23.dist-info/WHEEL
behavysis_classifier-0.1.23.dist-info/entry_points.txt
behavysis_classifier-0.1.23.dist-info/RECORD
