Metadata-Version: 2.1
Name: behavysis_classifier
Version: 0.1.23
Summary: Behaviour classifier for the behavysis suite
Home-page: https://tlee08.github.io/behavysis_classifier
License: LGPL-3.0-or-later
Author: BowenLab
Requires-Python: >=3.12,<4.0
Classifier: License :: OSI Approved :: GNU Lesser General Public License v3 or later (LGPLv3+)
Classifier: Programming Language :: Python :: 3
Classifier: Programming Language :: Python :: 3.12
Classifier: Programming Language :: Python :: 3.13
Requires-Dist: behavysis_core (>=0.1.3,<0.2.0)
Requires-Dist: imbalanced-learn (>=0.12.2,<0.13.0)
Requires-Dist: scikit-learn (>=1.4.2,<2.0.0)
Requires-Dist: streamlit (>=1.36.0,<2.0.0)
Requires-Dist: torch (>=2.2.2,<3.0.0)
Project-URL: Documentation, https://tlee08.github.io/behavysis_classifier
Project-URL: Repository, https://tlee08.github.io/behavysis_classifier
